MANIFEST.in
README.txt
setup.py
c2/__init__.py
c2.search.kananormalizer.egg-info/PKG-INFO
c2.search.kananormalizer.egg-info/SOURCES.txt
c2.search.kananormalizer.egg-info/dependency_links.txt
c2.search.kananormalizer.egg-info/entry_points.txt
c2.search.kananormalizer.egg-info/namespace_packages.txt
c2.search.kananormalizer.egg-info/not-zip-safe
c2.search.kananormalizer.egg-info/requires.txt
c2.search.kananormalizer.egg-info/top_level.txt
c2/search/__init__.py
c2/search/kananormalizer/__init__.py
c2/search/kananormalizer/configure.zcml
c2/search/kananormalizer/normalizer.py
c2/search/kananormalizer/tests.py
c2/search/kananormalizer/version.txt
c2/search/kananormalizer/profiles/default/catalog.xml
c2/search/kananormalizer/profiles/default/metadata.xml
docs/HISTORY.txt
docs/INSTALL.txt
docs/LICENSE.GPL
docs/LICENSE.txt