Metadata-Version: 1.1
Name: c2.search.kananormalizer
Version: 1.0a1
Summary: This package is Japanese KANA normalizer for Plone.
Home-page: https://bitbucket.org/cmscom/c2.search.kananormalizer
Author: Manabu TERADA
Author-email: terada@cmscom.jp
License: GPL
Keywords: plone search Japanese normalizer
Platform: UNKNOWN
Classifier: Framework :: Plone
Classifier: Programming Language :: Python
